bleongpkg/extra_time/__init__.py
bleongpkg/extra_time/now.py
bleongpkg/main.py
bleongpkg-0.1.1.dist-info/METADATA
bleongpkg-0.1.1.dist-info/WHEEL
bleongpkg-0.1.1.dist-info/entry_points.txt
bleongpkg-0.1.1.dist-info/RECORD
